<?xml version="1.0" encoding="UTF-8"?>
<!DOCTYPE texts SYSTEM "../../../../dtd/ewdtext.dtd">
<texts lang="en" pubno="EM3140CG" style="font-size:6px;font-family:'Arial'" ver="2.1.2.6">
	<text textID="1">* 2 :w/ Steering Pad Switch</text>
	<text textID="2">* 3 :w/o Steering Pad Switch</text>
	<text textID="3">HORN Relay</text>
	<text textID="4">High Pitched Horn Assembly</text>
	<text textID="5">Horn Button Wire Sub-Assembly</text>
	<text textID="6">Horn Switch</text>
	<text textID="7">Low Pitched Horn Assembly</text>
	<text textID="8">Spiral Cable Sub-Assembly</text>
	<text textID="9">Spiral Cable Sub-Assembly , Horn Button Wire Sub-Assembly</text>
	<text textID="10">Spiral Cable Sub-Assembly , Horn Button Wire Sub-Assembly , Steering Pad Switch Assembly</text>
	<text textID="11">Spiral Cable Sub-Assembly , Steering Pad Switch Assembly</text>
	<text textID="12">Steering Pad Switch Assembly</text>
</texts>
