<?xml version="1.0" encoding="UTF-8" standalone="no"?><tmc-service-sakuin-index><pub id="RM3140CG"><index label="N">
<parts p-type="2" parts-id="F0003ZT">
<name>铭牌</name>
</parts>
<parts p-type="2" parts-id="D1002QZ">
<name>导航系统</name>
</parts>
<parts p-type="2" parts-id="F0000C5">
<name>导航天线</name>
</parts>
<parts p-type="1" parts-id="86860">
<name>导航天线总成</name>
</parts>
<parts p-type="1" parts-id="86808">
<name>1 号导航天线芯线分总成</name>
</parts>
<parts p-type="2" parts-id="B802003">
<name>导航 ECU</name>
</parts>
<parts p-type="2" parts-id="F0000BQ">
<name>导航接收器</name>
</parts>
<parts p-type="1" parts-id="86120L">
<name>导航接收器总成</name>
</parts>
<parts p-type="2" parts-id="B803044">
<name>导航设定</name>
</parts>
<parts p-type="2" parts-id="B001516">
<name>未检测到故障</name>
</parts>
<parts p-type="2" parts-id="B000142">
<name>1 号气缸至 TDC/压缩</name>
</parts>
<parts p-type="2" parts-id="B001120">
<name>发动机 1 号吊架</name>
</parts>
<parts p-type="1" parts-id="13512">
<name>2 号凸轮轴</name>
</parts>
<parts p-type="1" parts-id="13507">
<name>2 号链条分总成</name>
</parts>
<parts p-type="2" parts-id="F0001V4">
<name>噪音情况</name>
</parts>
<parts p-type="2" parts-id="F0004A1">
<name>静噪滤波器</name>
</parts>
<parts p-type="2" parts-id="F0001V5">
<name>噪音源</name>
</parts>
</index></pub></tmc-service-sakuin-index>