<?xml version="1.0" encoding="UTF-8" standalone="no"?><tmc-service-sakuin-index><pub id="RM3140CG"><index label="A">
<parts p-type="2" parts-id="F0001AM">
<name>A</name>
</parts>
<parts p-type="2" parts-id="B190987">
<name>ACC CUT 继电器</name>
</parts>
<parts p-type="2" parts-id="B001900">
<name>加速踏板</name>
</parts>
<parts p-type="1" parts-id="78110K">
<name>加速踏板传感器总成</name>
</parts>
<parts p-type="1" parts-id="31483B">
<name>蓄压器至挠性软管的管</name>
</parts>
<parts p-type="3" parts-id="ZZZZZZ">
<name>主动测试  主动测试</name>
</parts>
<parts p-type="2" parts-id="B000002">
<name>执行器</name>
</parts>
<parts p-type="2" parts-id="B980074">
<name>加注制动液</name>
</parts>
<parts p-type="2" parts-id="B400556">
<name>调节螺母</name>
</parts>
<parts p-type="2" parts-id="B000005">
<name>调节垫片</name>
</parts>
<parts p-type="2" parts-id="F0003NL">
<name>受波干扰影响</name>
</parts>
<parts p-type="1" parts-id="89170A">
<name>气囊 ECU 总成</name>
</parts>
<parts p-type="1" parts-id="89174A">
<name>左前空气囊传感器</name>
</parts>
<parts p-type="1" parts-id="89173A">
<name>右前空气囊传感器</name>
</parts>
<parts p-type="1" parts-id="17705">
<name>空气滤清器盖分总成</name>
</parts>
<parts p-type="2" parts-id="B000007">
<name>空气滤清器壳</name>
</parts>
<parts p-type="1" parts-id="17701">
<name>空气滤清器壳分总成</name>
</parts>
<parts p-type="1" parts-id="17801">
<name>空气滤清器滤芯分总成</name>
</parts>
<parts p-type="1" parts-id="17751">
<name>1 号空气滤清器进气口</name>
</parts>
<parts p-type="2" parts-id="B800043">
<name>空调装置总成</name>
</parts>
<parts p-type="2" parts-id="F00003Y">
<name>空调系统</name>
</parts>
<parts p-type="2" parts-id="B909587">
<name>空调放大器</name>
</parts>
<parts p-type="1" parts-id="88650N">
<name>空调放大器总成</name>
</parts>
<parts p-type="1" parts-id="55900">
<name>空调控制总成</name>
</parts>
<parts p-type="2" parts-id="F0000IS">
<name>空调滤清器</name>
</parts>
<parts p-type="1" parts-id="82210K">
<name>空调线束总成</name>
</parts>
<parts p-type="2" parts-id="F0003W3">
<name>空调面板</name>
</parts>
<parts p-type="2" parts-id="B559200">
<name>空调面板总成</name>
</parts>
<parts p-type="2" parts-id="F000158">
<name>空调压力传感器</name>
</parts>
<parts p-type="1" parts-id="87050">
<name>空调散热器总成</name>
</parts>
<parts p-type="2" parts-id="M000112">
<name>空调系统</name>
</parts>
<parts p-type="2" parts-id="F0003VX">
<name>空调装置</name>
</parts>
<parts p-type="1" parts-id="87212">
<name>1 号后风管</name>
</parts>
<parts p-type="1" parts-id="87201B">
<name>2 号风管分总成</name>
</parts>
<parts p-type="1" parts-id="87201F">
<name>3 号风管分总成</name>
</parts>
<parts p-type="1" parts-id="88548B">
<name>空气滤清器壳</name>
</parts>
<parts p-type="1" parts-id="89467B">
<name>空燃比传感器</name>
</parts>
<parts p-type="2" parts-id="B894653">
<name>空燃比传感器</name>
</parts>
<parts p-type="2" parts-id="B894670">
<name>空燃比传感器</name>
</parts>
<parts p-type="2" parts-id="B400029">
<name>空气泄漏</name>
</parts>
<parts p-type="2" parts-id="B004004">
<name>气密性</name>
</parts>
<parts p-type="1" parts-id="17361M">
<name>空气管</name>
</parts>
<parts p-type="1" parts-id="88719A">
<name>空调压力传感器</name>
</parts>
<parts p-type="1" parts-id="88710">
<name>空调管总成</name>
</parts>
<parts p-type="1" parts-id="55909C">
<name>空气混合风门控制拉索分总成</name>
</parts>
<parts p-type="1" parts-id="87106H">
<name>空气混合风门伺服机构分总成</name>
</parts>
<parts p-type="2" parts-id="B800648">
<name>环境温度传感器</name>
</parts>
<parts p-type="2" parts-id="F0000C4">
<name>放大器天线</name>
</parts>
<parts p-type="1" parts-id="86300B">
<name>1 号放大器天线总成</name>
</parts>
<parts p-type="1" parts-id="86101">
<name>天线芯线分总成</name>
</parts>
<parts p-type="2" parts-id="B801004">
<name>天线型</name>
</parts>
<parts p-type="1" parts-id="04945">
<name>前消音垫片组件</name>
</parts>
<parts p-type="2" parts-id="B400613">
<name>后消音垫片组件</name>
</parts>
<parts p-type="2" parts-id="B980194">
<name>输出任何其他 DTC</name>
</parts>
<parts p-type="1" parts-id="88897P">
<name>吸气器</name>
</parts>
<parts p-type="1" parts-id="74630E">
<name>左后辅助拉手总成</name>
</parts>
<parts p-type="1" parts-id="74620C">
<name>右后辅助拉手总成</name>
</parts>
<parts p-type="1" parts-id="74610A">
<name>辅助拉手分总成</name>
</parts>
<parts p-type="2" parts-id="F000295">
<name>助力图写入</name>
</parts>
<parts p-type="2" parts-id="D12040Z">
<name>音频/视频系统</name>
</parts>
<parts p-type="2" parts-id="M000180">
<name>音频和视频系统</name>
</parts>
<parts p-type="2" parts-id="F0001V7">
<name>音响设定</name>
</parts>
<parts p-type="2" parts-id="B002955">
<name>Auto LSD Switch</name>
</parts>
<parts p-type="1" parts-id="89120A">
<name>自动灯光控制传感器</name>
</parts>
<parts p-type="2" parts-id="F0003ZD">
<name>自动灯光控制传感器</name>
</parts>
<parts p-type="2" parts-id="D1002BZ">
<name>自动传动桥</name>
</parts>
<parts p-type="2" parts-id="F0000HG">
<name>自动传动桥“驻车”机构</name>
</parts>
<parts p-type="2" parts-id="F000018">
<name>车桥系统</name>
</parts>
</index></pub></tmc-service-sakuin-index>